LICENSE
README.md
setup.py
test/test_pathutils.py
xleb/__main__.py
xleb/config.py
xleb/fapi.py
xleb/fmiddleware.py
xleb/pathutils.py
xleb/state.py
xleb.egg-info/PKG-INFO
xleb.egg-info/SOURCES.txt
xleb.egg-info/dependency_links.txt
xleb.egg-info/entry_points.txt
xleb.egg-info/requires.txt
xleb.egg-info/top_level.txt
xleb/static/auth.html
xleb/static/index.html
xleb/static/css/common.css
xleb/static/media/favicon.png